pycloudmusic163
