Metadata-Version: 2.1
Name: pycloudmusic163
Version: 0.1.1
Summary: 使用Python快速调用网易云音乐api
Home-page: https://github.com/FengLiuFeseliud/pycloudmusic163
Author: FengLiuFeseliud
Author-email: 17351198406@qq.com
License: UNKNOWN
Platform: any
Classifier: Programming Language :: Python :: 3
Classifier: License :: OSI Approved :: MIT License
Classifier: Operating System :: OS Independent
Requires-Python: >=3.7
License-File: LICENSE
